genuisfinder/__init__.py
genuisfinder/main.py
genuisfinder-0.1.1.dist-info/LICENSE
genuisfinder-0.1.1.dist-info/METADATA
genuisfinder-0.1.1.dist-info/WHEEL
genuisfinder-0.1.1.dist-info/top_level.txt
genuisfinder-0.1.1.dist-info/RECORD
